uno_template/__init__.py
uno_template-0.2.0.dist-info/LICENSE
uno_template-0.2.0.dist-info/METADATA
uno_template-0.2.0.dist-info/WHEEL
uno_template-0.2.0.dist-info/top_level.txt
uno_template-0.2.0.dist-info/RECORD
